Metadata-Version: 2.1
Name: ak-M2Crypto
Version: 0.26.1
Summary: M2Crypto: A Python crypto and SSL toolkit
Home-page: https://github.com/appknox/m2crypto
Author: Appknox
Author-email: engineer@appknox.com
Maintainer: Appknox
Maintainer-email: engineer@appknox.com
License: BSD-style license
Keywords: cryptography openssl
Platform: any
Classifier: Development Status :: 5 - Production/Stable
Classifier: Intended Audience :: Developers
Classifier: Operating System :: OS Independent
Classifier: Programming Language :: C
Classifier: Programming Language :: Python
Classifier: Topic :: Security :: Cryptography
Classifier: Topic :: Software Development :: Libraries :: Python Modules
Classifier: Programming Language :: Python :: 2
Classifier: Programming Language :: Python :: 2.6
Classifier: Programming Language :: Python :: 2.7
Requires-Dist: typing
